<?xml version="1.0"?>
<col:collection xmlns="http://cnx.rice.edu/collxml" xmlns:col="http://cnx.rice.edu/collxml" xml:lang="en" authors="Joseph Makolandra ,Kevin G. Bezy ,Cindy Delp ,Brad E. Bizzell ,Caroline Wray ,Forest Jones ,Janet Womack ,Dawn Hutton ,Asia Jones ,Guylene Wood-Setzer ,Seydric Williams ,Nancy Leonard ,Ken Nicely ,Linda Wright ,Robert Pennington ,Tracy Richardson">
  <metadata xmlns:md="http://cnx.rice.edu/mdml" mdml-version="0.5">
    <md:content-id>col10727</md:content-id>
    <md:title>21st Century Theories of Education Administration </md:title>
    <md:language>en</md:language>
    <md:license url="http://creativecommons.org/licenses/by/3.0/">Creative Commons Attribution License</md:license>
    <md:uuid>15788dd1-fbfc-4dbc-a85f-9c2b3f091728</md:uuid>
    <md:slug>21st-century-theories-of-education-administration</md:slug>
  </metadata>
  <col:content>
    <col:module document="m27142"/>
    <col:module document="m26885"/>
    <col:module document="m26652"/>
    <col:module document="m26889"/>
    <col:module document="m27130"/>
    <col:module document="m27080"/>
    <col:module document="m27825"/>
    <col:module document="m27177"/>
  </col:content>
</col:collection>
